{"CAAEviTechArticles": {"FileList":["CAAEviCMInterfaces.htm"],"TitleList":["The Change Management Interfaces"],"WordList":{"been":[1],"references":[1],"objects":[1],"acttype":[1],"null_var":[1],"clippartversion":[1],"these":[1],"reflect":[1],"would":[1],"hi-loks":[1],"drawing":[1],"you":[1],"cv1":[1],"enovicwaffectedobjects":[1],"successfully":[1],"using":[1],"caaeviecomanager":[1],"cout":[1],"documentation":[1],"dassault":[1],"completed":[1],"then":[1],"an":[1],"version":[1],"rc":[1],"as":[1],"contains":[1],"linkobj":[1],"reserved":[1],"domain":[1],"spcfgview":[1],"creating":[1],"returns":[1],"actions":[1],"object":[1],"succeeded":[1],"appropriate":[1],"be":[1],"cut":[1],"document":[1],"prodname":[1],"example":[1],"result":[1],"how":[1],"dsg123":[1],"routine":[1],"are":[1],"scenario":[1],"cativpmafllink.h":[1],"ecotype":[1],"enovinterfaces":[1],"creation":[1],"linked":[1],"a":[1],"set":[1],"manager":[1],"necessary":[1],"ecoinitialabstract":[1],"n":[1],"call":[1],"cativpmaflaffectedobject.h":[1],"p":[1],"the":[1],"calls":[1],"information":[1],"to":[1],"returned":[1],"operation":[1],"effid":[1],"controls":[1],"added":[1],"cativpmafllink_var":[1],"documents":[1],"clips":[1],"available":[1],"deliverable":[1],"lifecycle":[1],"view":[1],"accomplished":[1],"prior":[1],"enovicwaffectedobjects_var":[1],"adding":[1],"details":[1],"has":[1],"those":[1],"add":[1],"which":[1],"ensure":[1],"need":[1],"finally":[1],"this":[1],"its":[1],"ispaste":[1],"engineering":[1],"enovicwconfiguredviews":[1],"modification":[1],"article":[1],"actpriority":[1],"enovicwconfiguredviews.h":[1],"ecoeff":[1],"dwg1111":[1],"action_design":[1],"enoviboecomanager.h":[1],"demonstrate":[1],"ecotypecode":[1],"allow":[1],"however":[1],"next":[1],"some":[1],"enovicwaffectedobject":[1],"technical":[1],"catienovcmeco_var":[1],"catienovcmeffectivity.h":[1],"production":[1],"for":[1],"show":[1],"paste":[1],"interface":[1],"we":[1],"not":[1],"accomplish":[1],"previously":[1],"drawings":[1],"effectivities":[1],"now":[1],"scope":[1],"catunicodestring":[1],"passed":[1],"caaeviactionmanager":[1],"caaevilinks":[1],"views":[1],"actname":[1],"successful":[1],"ecopriority":[1],"effectivity":[1],"interfaces":[1],"types":[1],"cases":[1],"apply":[1],"false":[1],"perform":[1],"addaffectedobject":[1],"existing":[1],"with":[1],"dsgact":[1],"spactmgr":[1],"management":[1],"refer":[1],"createnewaction":[1],"typical":[1],"short":[1],"step":[1],"time":[1],"eco123":[1],"applications":[1],"catienovcmeffectivity_var":[1],"copyright":[1],"release":[1],"createdeliverablelink":[1],"type":[1],"beyond":[1],"when":[1],"required":[1],"caaeviaffectedobjects":[1],"cast":[1],"action":[1],"if":[1],"s_ok":[1],"case":[1],"enovicwconfiguredviews_var":[1],"order":[1],"method":[1],"affobj":[1],"in":[1],"createneweco":[1],"made":[1],"work":[1],"spaffobj":[1],"is":[1],"being":[1],"it":[1],"ecos":[1],"removing":[1],"samples":[1],"ecoversion":[1],"examples":[1],"following":[1],"quot":[1],"other":[1],"methods":[1],"direct":[1],"range":[1],"splink":[1],"cativpmaflaffectedobject_var":[1],"top":[1],"catiaflaction.h":[1],"indicates":[1],"rights":[1],"have":[1],"member":[1],"mod1":[1],"dsgaction":[1],"enovicwaffectedobjects.h":[1],"editor":[1],"include":[1],"product":[1],"specomgr":[1],"within":[1],"more":[1],"change":[1],"ecrtypecode":[1],"abstract":[1],"framework":[1],"addnewecoeffectivity":[1],"future":[1],"e_fail":[1],"certain":[1],"clip":[1],"first":[1],"feb":[1],"instance":[1],"use":[1],"econame":[1],"enovicwlinks.h":[1],"eco":[1],"that":[1],"shows":[1],"shown":[1],"create":[1],"from":[1],"links":[1],"different":[1],"enovia_cmaffected_object":[1],"effecitivity":[1],"all":[1],"configured":[1],"new":[1],"including":[1],"link-to":[1],"below":[1],"like":[1],"created":[1],"history":[1],"affected":[1],"catunicodestring.h":[1],"produced":[1],"aotype":[1],"catienovcmeco.h":[1],"creates":[1],"basic":[1],"systèmes":[1],"note":[1],"code":[1],"part":[1],"link":[1],"statements":[1],"can":[1],"operations":[1],"structural":[1],"and":[1],"intended":[1],"design":[1],"of":[1],"working":[1],"enovicwlinks":[1],"adds":[1],"on":[1],"cativpmaflaction_var":[1],"will":[1],"enoviboactionmanager.h":[1],"cativpmaflaction":[1],"also":[1],"control":[1],"boolean":[1],"listed":[1],"actinitialabstract":[1],"catienovcmeco":[1],"fasteners":[1],"variable":[1],"arguments":[1],"uses":[1],"caaeviconfiguredviews":[1],"simply":[1]}}}