{"CAAScdRscTechArticles": {"FileList":["CAARscTocRealTimeRendering.htm"],"TitleList":["Real Time Rendering Automation Objects"],"WordList":{"copyright":[1],"cylindrical":[1],"legend":[1],"objects":[1],"positionned":[1],"accessed":[1],"clights":[1],"type":[1],"three":[1],"defines":[1],"1999-2013":[1],"accessing":[1],"depending":[1],"collections":[1],"property":[1],"viewpoint":[1],"using":[1],"method":[1],"shape":[1],"in":[1],"renderingenvironments":[1],"renderinglights":[1],"dassault":[1],"is":[1],"rendering":[1],"limiting":[1],"an":[1],"click":[1],"as":[1],"renderingenvironment":[1],"light":[1],"reserved":[1],"obtained":[1],"object":[1],"be":[1],"document":[1],"are":[1],"rights":[1],"camera":[1],"lights":[1],"a":[1],"product":[1],"set":[1],"cshoots":[1],"may":[1],"more":[1],"texture":[1],"one":[1],"representing":[1],"abstract":[1],"performed":[1],"the":[1],"such":[1],"shootings":[1],"catrscrenderingenvironmentvbext":[1],"to":[1],"faces":[1],"chart":[1],"return":[1],"through":[1],"arrow":[1],"environments":[1],"dim":[1],"screen":[1],"renderingshootings":[1],"source":[1],"orootproduct.getitem":[1],"space":[1],"userrenderinglights":[1],"3d":[1],"that":[1],"automation":[1],"zone":[1],"from":[1],"has":[1],"those":[1],"described":[1],"all":[1],"renderingenvironmentwall":[1],"visible":[1],"below":[1],"catrscrenderingshootingvbext":[1],"capture":[1],"its":[1],"cenvs":[1],"collection":[1],"real":[1],"expand":[1],"catproduct":[1],"oriented":[1],"support":[1],"systèmes":[1],"sources":[1],"origin":[1],"spherical":[1],"renderinglight":[1],"catrscrenderinglightvbext":[1],"can":[1],"not":[1],"and":[1],"renderingshooting":[1],"of":[1],"root":[1],"definition":[1],"direction":[1],"on":[1],"cubic":[1],"or":[1],"captures":[1],"previous":[1],"getitem":[1],"environment":[1],"time":[1]}}}