{"CAAOptTechArticles": {"FileList":["CAAOptGlossary.htm"],"TitleList":["KnowledgeOptimizer Glossary"],"WordList":{"copyright":[1],"references":[1],"criteria":[1],"reach":[1],"objects":[1],"about":[1],"maximization":[1],"during":[1],"constraints":[1],"required":[1],"defines":[1],"objective":[1],"equations":[1],"output":[1],"problem":[1],"depending":[1],"optimization":[1],"context":[1],"peo":[1],"persistent":[1],"you":[1],"algorithm":[1],"goals":[1],"knowledge":[1],"give":[1],"using":[1],"goal":[1],"in":[1],"ouputs":[1],"made":[1],"dassault":[1],"understand":[1],"is":[1],"it":[1],"priority":[1],"an":[1],"version":[1],"each":[1],"inequations":[1],"input":[1],"as":[1],"concepts":[1],"reserved":[1],"optimizations":[1],"algorithms":[1],"be":[1],"fact":[1],"document":[1],"optimizationinterfaces":[1],"eventually":[1],"talking":[1],"literal":[1],"how":[1],"vocabulary":[1],"top":[1],"are":[1],"rights":[1],"term":[1],"where":[1],"free":[1],"knowledgeinterfaces":[1],"knows":[1],"a":[1],"product":[1],"set":[1],"acronym":[1],"abstract":[1],"right":[1],"satisfaction":[1],"produce":[1],"describes":[1],"the":[1],"framework":[1],"ppr":[1],"associated":[1],"maximum":[1],"constraint":[1],"information":[1],"to":[1],"minimum":[1],"open":[1],"v5":[1],"outputs":[1],"inputs":[1],"own":[1],"several":[1],"solved":[1],"used":[1],"definiton":[1],"3d":[1],"derivatives":[1],"features":[1],"that":[1],"etc":[1],"find":[1],"knowledgeadvisor":[1],"results":[1],"selected":[1],"all":[1],"which":[1],"actual":[1],"dedicated":[1],"settings":[1],"like":[1],"created":[1],"solutions":[1],"this":[1],"includes":[1],"engineering":[1],"history":[1],"article":[1],"respect":[1],"glossary":[1],"ending":[1],"external":[1],"minimization":[1],"modeler":[1],"solve":[1],"produces":[1],"parameters":[1],"updated":[1],"systèmes":[1],"changed":[1],"problems":[1],"some":[1],"code":[1],"solving":[1],"ranges":[1],"technical":[1],"purpose":[1],"additional":[1],"concept":[1],"for":[1],"their":[1],"objectspecsmodeler":[1],"interface":[1],"speed":[1],"we":[1],"can":[1],"general":[1],"numerical":[1],"producing":[1],"nov":[1],"optimizer":[1],"relies":[1],"and":[1],"of":[1],"parameter":[1],"definition":[1],"value":[1],"adds":[1],"on":[1],"or":[1],"will":[1],"introduce":[1],"perform":[1],"way":[1],"target":[1],"plm":[1],"with":[1],"sensors":[1],"what":[1],"hub":[1],"manipulating":[1],"there":[1],"ones":[1],"strategy":[1],"user":[1],"gateway":[1],"customer":[1]}}}